Metadata-Version: 2.4
Name: skip-django-chamber
Version: 9.0.0
Summary: Utilities library meant as a complement to django-is-core.
Home-page: http://github.com/skip-pay/django-chamber
Author: Lubos Matl, Oskar Hollmann
Author-email: matllubos@gmail.com, oskar@hollmann.me
Classifier: Development Status :: 4 - Beta
Classifier: Environment :: Web Environment
Classifier: Intended Audience :: Developers
Classifier: License :: OSI Approved :: GNU Library or Lesser General Public License (LGPL)
Classifier: Operating System :: OS Independent
Classifier: Programming Language :: Python
Classifier: Programming Language :: Python :: 3.6
Classifier: Programming Language :: Python :: 3.7
Classifier: Programming Language :: Python :: 3.8
Classifier: Programming Language :: Python :: 3.9
Classifier: Programming Language :: Python :: 3.10
Classifier: Programming Language :: Python :: 3.11
Classifier: Framework :: Django
Requires-Python: >=3.6
License-File: LICENSE
Requires-Dist: django>=4.2
Requires-Dist: Unidecode>=1.1.1
Requires-Dist: pyprind>=2.11.2
Requires-Dist: python-magic>=0.4.27
Provides-Extra: boto3storage
Requires-Dist: django-storages<2.0; extra == "boto3storage"
Requires-Dist: boto3; extra == "boto3storage"
Dynamic: author
Dynamic: author-email
Dynamic: classifier
Dynamic: home-page
Dynamic: license-file
Dynamic: provides-extra
Dynamic: requires-dist
Dynamic: requires-python
Dynamic: summary
